{"name":"Search - Inactive","id":"stories/Universal_Nav/Site Search.story;Search - Inactive","testSteps":[{"number":1,"description":"Given user is on the OCOM  page","duration":10147,"startTime":"2018-11-08T20:18:59.363+05:30[Asia/Calcutta]","screenshots":[{"screenshot":"01914ad83b104b1fe28916d0c583f724917d57bf0f2cf0481fa3828c70d69193.png"}],"result":"SUCCESS","precondition":false,"children":[{"number":2,"description":"Is the home page","duration":5922,"startTime":"2018-11-08T20:18:59.373+05:30[Asia/Calcutta]","screenshots":[{"screenshot":"c31e69cfd9276d0c254ef4ce495c3b449c29d333792da0e3906f95ddb9db14ed.png"}],"result":"SUCCESS","precondition":false},{"number":3,"description":"Maximize browser","duration":3881,"startTime":"2018-11-08T20:19:05.296+05:30[Asia/Calcutta]","screenshots":[{"screenshot":"c31e69cfd9276d0c254ef4ce495c3b449c29d333792da0e3906f95ddb9db14ed.png"},{"screenshot":"01914ad83b104b1fe28916d0c583f724917d57bf0f2cf0481fa3828c70d69193.png"}],"result":"SUCCESS","precondition":false}]},{"number":4,"description":"When Global nav loads","duration":6285,"startTime":"2018-11-08T20:19:09.511+05:30[Asia/Calcutta]","screenshots":[{"screenshot":"01914ad83b104b1fe28916d0c583f724917d57bf0f2cf0481fa3828c70d69193.png"}],"result":"SUCCESS","precondition":false,"children":[{"number":5,"description":"Is the home page","duration":2145,"startTime":"2018-11-08T20:19:09.863+05:30[Asia/Calcutta]","screenshots":[{"screenshot":"01914ad83b104b1fe28916d0c583f724917d57bf0f2cf0481fa3828c70d69193.png"}],"result":"SUCCESS","precondition":false},{"number":6,"description":"Maximize browser","duration":2691,"startTime":"2018-11-08T20:19:12.009+05:30[Asia/Calcutta]","screenshots":[{"screenshot":"01914ad83b104b1fe28916d0c583f724917d57bf0f2cf0481fa3828c70d69193.png"}],"result":"SUCCESS","precondition":false},{"number":7,"description":"Global nav loads","duration":737,"startTime":"2018-11-08T20:19:14.701+05:30[Asia/Calcutta]","screenshots":[{"screenshot":"01914ad83b104b1fe28916d0c583f724917d57bf0f2cf0481fa3828c70d69193.png"}],"result":"SUCCESS","precondition":false}]},{"number":8,"description":"Then Search text must be followed with a search icon","duration":1388,"startTime":"2018-11-08T20:19:15.796+05:30[Asia/Calcutta]","screenshots":[{"screenshot":"01914ad83b104b1fe28916d0c583f724917d57bf0f2cf0481fa3828c70d69193.png"}],"result":"SUCCESS","precondition":false,"children":[{"number":9,"description":"Is search icon display","duration":682,"startTime":"2018-11-08T20:19:16.180+05:30[Asia/Calcutta]","screenshots":[{"screenshot":"01914ad83b104b1fe28916d0c583f724917d57bf0f2cf0481fa3828c70d69193.png"}],"result":"SUCCESS","precondition":false}]}],"userStory":{"id":"Site Search","storyName":"Site Search","path":"Universal_Nav/Site Search.story","narrative":"In order to communicate effectively to the business some functionality\nAs a development team\nI want to use Behaviour-Driven Development\n\neta:@skip","type":"story"},"featureTag":{"name":"Universal  nav/Site Search","type":"story"},"title":"Search - Inactive","tags":[{"name":"Universal nav","type":"feature"},{"name":"chrome","type":"browser"},{"name":"chrome","type":"context"},{"name":"Universal nav/Site search","type":"story"}],"startTime":"2018-11-08T20:18:59.362+05:30[Asia/Calcutta]","duration":17823,"projectKey":"","sessionId":"831bf964f3e549e64fdbca21a782ebac","driver":"chrome","context":"chrome","manual":false,"testSource":"JBehave","result":"SUCCESS"}